emq_celery/__init__.py
emq_celery/producer.py
emq_celery/transport.py
emq_celery-3.0.6.dist-info/DESCRIPTION.rst
emq_celery-3.0.6.dist-info/METADATA
emq_celery-3.0.6.dist-info/RECORD
emq_celery-3.0.6.dist-info/WHEEL
emq_celery-3.0.6.dist-info/metadata.json
emq_celery-3.0.6.dist-info/top_level.txt
