Metadata-Version: 2.0
Name: emq-celery
Version: 3.0.6
Summary: 用于使用EMQ来做为Celery的Broker
Home-page: http://xiangyang.li/project/emq_celery
Author: Shawn Li
Author-email: shawn@xiangyang.li
License: MIT License
Keywords: emq,celery
Platform: any
Requires-Dist: galaxy-sdk-python (>=0.2.3)
